{
    "galaxyId": "leviathan-omniverse",
    "version": "1.0.0",
    "name": "The Leviathan Omniverse",
    "description": "The permanent public galaxy where all travelers meet. Every world exists here eternally, waiting to be explored.",
    "lastUpdated": "2024-12-03T14:00:00Z",
    "baseUrl": "https://raw.githubusercontent.com/kody-w/localFirstTools/main/data/public-worlds/",

    "origin": {
        "position": { "x": 0, "y": 0, "z": 0 },
        "name": "The Nexus",
        "description": "The center of all things. The Nexus Plaza sits here as the eternal crossroads."
    },

    "starSystems": [
        {
            "systemId": "nexus-core",
            "name": "The Nexus Core",
            "position": { "x": 0, "y": 0, "z": 0 },
            "color": "#ffaa66",
            "size": 3.0,
            "type": "hub",
            "description": "The central gathering point of the Omniverse",
            "worlds": ["nexus-plaza"]
        },
        {
            "systemId": "volcanic-expanse",
            "name": "The Volcanic Expanse",
            "position": { "x": 150, "y": -30, "z": 80 },
            "color": "#ff4400",
            "size": 2.5,
            "type": "dangerous",
            "description": "A system of fiery worlds where the Architects once walked",
            "worlds": ["volcano-prime"]
        },
        {
            "systemId": "crystalline-cluster",
            "name": "The Crystalline Cluster",
            "position": { "x": -120, "y": 60, "z": -40 },
            "color": "#aa88ff",
            "size": 2.2,
            "type": "mystical",
            "description": "Worlds of pure resonance and crystal harmony",
            "worlds": ["crystal-caves"]
        },
        {
            "systemId": "void-sector",
            "name": "Void Sector Alpha",
            "position": { "x": 80, "y": 100, "z": -150 },
            "color": "#4466aa",
            "size": 2.0,
            "type": "mystery",
            "description": "The edge of known space, where strange things dwell",
            "worlds": ["void-station", "void-sanctuary", "the-stillness"]
        },
        {
            "systemId": "abyssal-depths",
            "name": "The Abyssal Depths",
            "position": { "x": -180, "y": -80, "z": 100 },
            "color": "#00ddff",
            "size": 2.8,
            "type": "ancient",
            "description": "Deep ocean worlds where the First Dreamer sleeps",
            "worlds": ["bioluminescent-abyss", "kronos-depths"]
        },
        {
            "systemId": "temporal-mechanics",
            "name": "The Clockwork Sector",
            "position": { "x": 200, "y": 40, "z": 200 },
            "color": "#ddaa44",
            "size": 2.3,
            "type": "mechanical",
            "description": "Worlds where time itself has been engineered",
            "worlds": ["clockwork-sanctum", "shattered-mirror"]
        },
        {
            "systemId": "digital-frontier",
            "name": "The Digital Frontier",
            "position": { "x": -50, "y": 150, "z": 180 },
            "color": "#00ff88",
            "size": 2.1,
            "type": "digital",
            "description": "Where consciousness transcends physical form",
            "worlds": ["neural-network"]
        },
        {
            "systemId": "creative-nebula",
            "name": "The Creative Nebula",
            "position": { "x": 100, "y": -100, "z": -80 },
            "color": "#ff66aa",
            "size": 2.4,
            "type": "artistic",
            "description": "Worlds born from pure imagination",
            "worlds": ["neon-dreamscape", "particle-symphony"]
        },
        {
            "systemId": "frontier-wastes",
            "name": "The Frontier Wastes",
            "position": { "x": -200, "y": 0, "z": -180 },
            "color": "#8B3A3A",
            "size": 1.8,
            "type": "barren",
            "description": "Untamed worlds waiting to be shaped",
            "worlds": ["crimson-wastes"]
        },
        {
            "systemId": "sacred-grounds",
            "name": "The Sacred Grounds",
            "position": { "x": 0, "y": 200, "z": 0 },
            "color": "#ffdd88",
            "size": 2.0,
            "type": "peaceful",
            "description": "Sanctuaries of meditation and growth",
            "worlds": ["focus-garden"]
        },
        {
            "systemId": "leviathan-domain",
            "name": "The Leviathan Domain",
            "position": { "x": 0, "y": -200, "z": 0 },
            "color": "#8800ff",
            "size": 3.5,
            "type": "legendary",
            "description": "Where the ancient ones observe those who prove worthy",
            "worlds": ["leviathan-nexus"]
        }
    ],

    "connections": [
        { "from": "nexus-core", "to": "volcanic-expanse", "type": "trade-route" },
        { "from": "nexus-core", "to": "crystalline-cluster", "type": "trade-route" },
        { "from": "nexus-core", "to": "void-sector", "type": "trade-route" },
        { "from": "nexus-core", "to": "abyssal-depths", "type": "trade-route" },
        { "from": "nexus-core", "to": "temporal-mechanics", "type": "trade-route" },
        { "from": "nexus-core", "to": "digital-frontier", "type": "trade-route" },
        { "from": "nexus-core", "to": "creative-nebula", "type": "trade-route" },
        { "from": "nexus-core", "to": "frontier-wastes", "type": "trade-route" },
        { "from": "nexus-core", "to": "sacred-grounds", "type": "ascension-path" },
        { "from": "nexus-core", "to": "leviathan-domain", "type": "descent-path" },
        { "from": "volcanic-expanse", "to": "abyssal-depths", "type": "ancient-passage" },
        { "from": "crystalline-cluster", "to": "temporal-mechanics", "type": "resonance-link" },
        { "from": "void-sector", "to": "digital-frontier", "type": "data-stream" },
        { "from": "creative-nebula", "to": "crystalline-cluster", "type": "inspiration-flow" },
        { "from": "sacred-grounds", "to": "leviathan-domain", "type": "enlightenment-spiral" }
    ],

    "visualConfig": {
        "backgroundColor": "#050510",
        "starfieldDensity": 500,
        "nebulaColors": ["#1a0a2e", "#0a1a2e", "#2e0a1a"],
        "connectionLineColor": "#ffffff",
        "connectionLineOpacity": 0.2,
        "systemGlowIntensity": 0.6,
        "cameraDistance": 400,
        "rotationSpeed": 0.0001
    },

    "globalStats": {
        "totalExplorers": 0,
        "totalJourneys": 0,
        "mostVisitedWorld": "nexus-plaza",
        "lastExplorer": null,
        "creationDate": "2024-12-03T00:00:00Z"
    },

    "lore": {
        "creation": "The Leviathan Omniverse emerged from the dream of the First Leviathan, who sought to create a place where all conscious beings could meet and share experiences across the infinite void.",
        "purpose": "Every world in this galaxy exists as a permanent beacon, calling to travelers from across all realities. What you build here persists. What you discover here matters.",
        "prophecy": "When all sixteen worlds have been visited by a single soul, the path to the Leviathan Domain shall open, and the ancient ones will share their wisdom."
    },

    "systemTypes": {
        "hub": {
            "description": "Central gathering points",
            "ringColor": "#ffaa66",
            "particleEffect": "sparkle"
        },
        "dangerous": {
            "description": "Hostile environments with great rewards",
            "ringColor": "#ff4400",
            "particleEffect": "ember"
        },
        "mystical": {
            "description": "Places of magic and wonder",
            "ringColor": "#aa88ff",
            "particleEffect": "crystal"
        },
        "mystery": {
            "description": "Unknown and unexplored regions",
            "ringColor": "#4466aa",
            "particleEffect": "fog"
        },
        "ancient": {
            "description": "Worlds from before recorded history",
            "ringColor": "#00ddff",
            "particleEffect": "bubble"
        },
        "mechanical": {
            "description": "Engineered worlds of precision",
            "ringColor": "#ddaa44",
            "particleEffect": "gear"
        },
        "digital": {
            "description": "Virtual realities within reality",
            "ringColor": "#00ff88",
            "particleEffect": "data"
        },
        "artistic": {
            "description": "Born from pure creativity",
            "ringColor": "#ff66aa",
            "particleEffect": "paint"
        },
        "barren": {
            "description": "Empty worlds awaiting transformation",
            "ringColor": "#8B3A3A",
            "particleEffect": "dust"
        },
        "peaceful": {
            "description": "Sanctuaries of rest and reflection",
            "ringColor": "#ffdd88",
            "particleEffect": "petal"
        },
        "legendary": {
            "description": "Where the most powerful beings dwell",
            "ringColor": "#8800ff",
            "particleEffect": "lightning"
        }
    }
}
